easyBio/SetupBioEnv.py
easyBio/__init__.py
easyBio/changeSRAName.py
easyBio/downloadSRA.py
easyBio/easyBio.py
easyBio/gsaPipline.py
easyBio/installConda copy.py
easyBio/installConda.py
easyBio/pipline.py
easyBio/run_cellranger.py
easyBio/runvelocyto.py
easyBio/splitSRA.py
easyBio/test.py
easyBio/tidy.py
easyBio/Utils/GeneSetScraper.py
easyBio/Utils/__init__.py
easyBio/Utils/downLoadBAM.py
easyBio/Utils/downLoadSRA.py
easyBio/Utils/download.py
easyBio/Utils/downloadUtils.py
easyBio/Utils/easyBioUtils.py
easyBio/Utils/easyCellranger.py
easyBio/Utils/gsaDownLoadUtils.py
easyBio/Utils/netUtils.py
easyBio/Utils/runvelocityc.py
easyBio/Utils/toFastq.py
easyBio/Utils/toolsUtils.py
easyBio/Utils/weChatRobot.py
easybio-0.5.4.dist-info/METADATA
easybio-0.5.4.dist-info/WHEEL
easybio-0.5.4.dist-info/entry_points.txt
easybio-0.5.4.dist-info/top_level.txt
easybio-0.5.4.dist-info/RECORD
