Metadata-Version: 2.1
Name: easybio
Version: 0.5.4
Summary: The purpose of the creation of this package is to make bioinformatics analysis simpler.
Home-page: https://github.com/xleizi/easyBio_conda
Author: Lei Cui
Author-email: cuilei798@qq.com
Maintainer: Lei Cui
Maintainer-email: cuilei798@qq.com
License: MIT License
Platform: linux
Classifier: Operating System :: OS Independent
Classifier: License :: OSI Approved :: MIT License
Classifier: Programming Language :: Python :: 3
Requires-Python: >=3
Requires-Dist: bs4
Requires-Dist: importlib-metadata
Requires-Dist: pandas
Requires-Dist: psutil
Requires-Dist: requests
Requires-Dist: threadpool
